robotgpt/__init__.py
robotgpt/api_requestor.py
robotgpt/api_resource.py
robotgpt/chat_completion.py
robotgpt/engine_api_resource.py
robotgpt/error.py
robotgpt/robotgpt.py
robotgpt/robotgpt_object.py
robotgpt/robotgpt_response.py
robotgpt/util.py
robotgpt-0.0.14.dist-info/LICENSE
robotgpt-0.0.14.dist-info/METADATA
robotgpt-0.0.14.dist-info/WHEEL
robotgpt-0.0.14.dist-info/top_level.txt
robotgpt-0.0.14.dist-info/RECORD
