Metadata-Version: 2.1
Name: robotgpt
Version: 0.0.14
Summary: RobotGPT LLM 支持Langchain
Home-page: UNKNOWN
Author: blaze.zhang
Author-email: blaze.zhang@cloudminds.com
License: UNKNOWN
Platform: UNKNOWN
Requires-Dist: langchain
